{
   "children" : [
      {
         "children" : [
            {
               "children" : [
                  {
                     "children" : [
                        {
                           "children" : [
                              {
                                 "children" : [
                                    {
                                       "children" : [
                                          {
                                             "children" : [
                                                {
                                                   "children" : [
                                                      "1"
                                                   ],
                                                   "rule" : "Number",
                                                   "span" : [
                                                      0,
                                                      1
                                                   ]
                                                }
                                             ],
                                             "rule" : "Literal",
                                             "span" : [
                                                0,
                                                1
                                             ]
                                          }
                                       ],
                                       "rule" : "Expression",
                                       "span" : [
                                          0,
                                          1
                                       ]
                                    },
                                    "+",
                                    {
                                       "children" : [
                                          {
                                             "children" : [
                                                {
                                                   "children" : [
                                                      "2"
                                                   ],
                                                   "rule" : "Number",
                                                   "span" : [
                                                      4,
                                                      5
                                                   ]
                                                }
                                             ],
                                             "rule" : "Literal",
                                             "span" : [
                                                4,
                                                5
                                             ]
                                          }
                                       ],
                                       "rule" : "Expression",
                                       "span" : [
                                          4,
                                          5
                                       ]
                                    }
                                 ],
                                 "rule" : "ArithmeticOp",
                                 "span" : [
                                    0,
                                    5
                                 ]
                              }
                           ],
                           "rule" : "Expression",
                           "span" : [
                              0,
                              5
                           ]
                        }
                     ],
                     "rule" : "ExpressionList",
                     "span" : [
                        0,
                        5
                     ]
                  }
               ],
               "rule" : "Statement",
               "span" : [
                  0,
                  5
               ]
            }
         ],
         "rule" : "StatementList",
         "span" : [
            0,
            5
         ]
      }
   ],
   "rule" : "Program",
   "span" : [
      0,
      5
   ]
}
