{
   "entry" : "node_27",
   "nodes" : [
      {
         "attributes" : {
            "condition_id" : "node_10"
         },
         "id" : "node_11",
         "inputs" : [
            "node_9",
            "node_10"
         ],
         "op" : "If"
      },
      {
         "attributes" : {
            "function_name" : "main",
            "params" : []
         },
         "id" : "node_25",
         "inputs" : [],
         "op" : "Start"
      },
      {
         "attributes" : {
            "type" : "Int",
            "value" : 1
         },
         "id" : "node_10",
         "inputs" : [
            "node_9"
         ],
         "op" : "Constant"
      },
      {
         "attributes" : {},
         "id" : "node_14",
         "inputs" : [
            "node_13"
         ],
         "op" : "Region"
      },
      {
         "attributes" : {
            "function_name" : "main",
            "params" : []
         },
         "id" : "node_9",
         "inputs" : [],
         "op" : "Start"
      },
      {
         "attributes" : {
            "index" : 1,
            "label" : "IfFalse"
         },
         "id" : "node_13",
         "inputs" : [
            "node_11"
         ],
         "op" : "Proj"
      },
      {
         "attributes" : {
            "type" : "Int",
            "value" : null
         },
         "id" : "node_26",
         "inputs" : [
            "node_25"
         ],
         "op" : "Constant"
      },
      {
         "attributes" : {
            "control_id" : "node_14",
            "value_id" : "node_26"
         },
         "id" : "node_27",
         "inputs" : [
            "node_14",
            "node_26"
         ],
         "op" : "Return"
      }
   ],
   "version" : "1.0"
}
