{
   "entry" : "node_18",
   "nodes" : [
      {
         "attributes" : {
            "type" : "Int",
            "value" : null
         },
         "id" : "node_17",
         "inputs" : [
            "node_16"
         ],
         "op" : "Constant"
      },
      {
         "attributes" : {
            "function_name" : "main",
            "params" : []
         },
         "id" : "node_16",
         "inputs" : [],
         "op" : "Start"
      },
      {
         "attributes" : {
            "control_id" : "node_16",
            "value_id" : "node_17"
         },
         "id" : "node_18",
         "inputs" : [
            "node_16",
            "node_17"
         ],
         "op" : "Return"
      }
   ],
   "version" : "1.0"
}
